spacesavvy/__init__.py
spacesavvy/common.py
spacesavvy/spacesavvy.py
spacesavvy-0.0.1.dist-info/LICENSE
spacesavvy-0.0.1.dist-info/METADATA
spacesavvy-0.0.1.dist-info/WHEEL
spacesavvy-0.0.1.dist-info/entry_points.txt
spacesavvy-0.0.1.dist-info/top_level.txt
spacesavvy-0.0.1.dist-info/RECORD
